mcp_server_llmling/__init__.py
mcp_server_llmling/__main__.py
mcp_server_llmling/cli/__init__.py
mcp_server_llmling/cli/install.py
mcp_server_llmling/config_resources/mcp_zed.yml
mcp_server_llmling/constants.py
mcp_server_llmling/conversions.py
mcp_server_llmling/handlers.py
mcp_server_llmling/http_client.py
mcp_server_llmling/injection/__init__.py
mcp_server_llmling/injection/models.py
mcp_server_llmling/injection/routes.py
mcp_server_llmling/injection/server.py
mcp_server_llmling/injection/utils.py
mcp_server_llmling/log.py
mcp_server_llmling/mcp_inproc_session.py
mcp_server_llmling/py.typed
mcp_server_llmling/server.py
mcp_server_llmling/server_federation.py
mcp_server_llmling/testing.py
mcp_server_llmling/ui/__init__.py
mcp_server_llmling/ui/app.py
mcp_server_llmling/ui/components/__init__.py
mcp_server_llmling/ui/components/header.py
mcp_server_llmling/ui/components/resource_list.py
mcp_server_llmling/ui/components/tool_list.py
mcp_server_llmling/ui/pages/__init__.py
mcp_server_llmling/ui/pages/dashboard.py
mcp_server_llmling/ui/pages/resources.py
mcp_server_llmling/ui/pages/tools.py
mcp_server_llmling/zed_wrapper.py
mcp_server_llmling-1.0.0.dist-info/WHEEL
mcp_server_llmling-1.0.0.dist-info/entry_points.txt
mcp_server_llmling-1.0.0.dist-info/METADATA
mcp_server_llmling-1.0.0.dist-info/RECORD
