Metadata-Version: 2.3
Name: mcp-server-llmling
Version: 1.0.0
Summary: MCP (Model context protocol) server with LLMling backend
Keywords: 
Author: Philipp Temminghoff
Author-email: Philipp Temminghoff <philipptemminghoff@googlemail.com>
License: MIT License
Classifier: Development Status :: 4 - Beta
Classifier: Framework :: Pydantic
Classifier: Framework :: Pydantic :: 2
Classifier: Intended Audience :: Developers
Classifier: Operating System :: OS Independent
Classifier: Programming Language :: Python :: 3
Classifier: Programming Language :: Python :: 3 :: Only
Classifier: Programming Language :: Python :: 3.12
Classifier: Programming Language :: Python :: 3.13
Classifier: Programming Language :: Python :: 3.14
Classifier: Topic :: Documentation
Classifier: Topic :: Software Development
Classifier: Topic :: Utilities
Classifier: Typing :: Typed
Requires-Dist: anyenv>=0.5.0
Requires-Dist: fastapi[standard]>=0.115.6
Requires-Dist: fastmcp>=2.3.4
Requires-Dist: llmling>=1.0.0
Requires-Dist: logfire>=2.6.2
Requires-Dist: mcp>=1.1.0
Requires-Dist: pydantic
Requires-Dist: universal-pathlib>=0.2.5
Requires-Dist: upathtools[httpx]
Requires-Dist: uvicorn
Requires-Dist: websockets>=14.1
Requires-Dist: nicegui ; extra == 'gui'
Requires-Python: >=3.13
Project-URL: Code coverage, https://app.codecov.io/gh/phil65/mcp-server-llmling
Project-URL: Discussions, https://github.com/phil65/mcp-server-llmling/discussions
Project-URL: Documentation, https://phil65.github.io/mcp-server-llmling/
Project-URL: Issues, https://github.com/phil65/mcp-server-llmling/issues
Project-URL: Source, https://github.com/phil65/mcp-server-llmling
Provides-Extra: gui
